setup.py
django_templatecomponents.egg-info/PKG-INFO
django_templatecomponents.egg-info/SOURCES.txt
django_templatecomponents.egg-info/dependency_links.txt
django_templatecomponents.egg-info/not-zip-safe
django_templatecomponents.egg-info/top_level.txt
management/__init__.py
management/commands/__init__.py
management/commands/generate_templatecomponents.py
templatecomponents/__init__.py
templatecomponents/models.py
templatecomponents/tests.py
templatecomponents/views.py
templatecomponents/management/__init__.py
templatecomponents/management/commands/__init__.py
templatecomponents/management/commands/generate_templatecomponents.py
templatecomponents/templatetags/__init__.py
templatecomponents/templatetags/templatecomponenttags.py
