Metadata-Version: 1.0
Name: django-templatecomponents
Version: 0.03
Summary: django-templatecomponents
Home-page: http://j03.de/projects/django-templatecomponents/
Author: Filip Noetzel
Author-email: UNKNOWN
License: Beerware
Keywords: templates,django
Platform: UNKNOWN
Classifier: Development Status :: 4 - Beta
Classifier: Programming Language :: Python
Classifier: Topic :: Software Development :: Libraries :: Python Modules
Classifier: Framework :: Django
Classifier: Environment :: Web Environment
